{
    "/dev/html/js/24-hour-lab.js": "/dev/html/js/24-hour-lab.js",
    "/dev/html/js/api-live.js": "/dev/html/js/api-live.js",
    "/dev/html/js/auto-scroll.js": "/dev/html/js/auto-scroll.js",
    "/dev/html/js/closed-lab.js": "/dev/html/js/closed-lab.js",
    "/dev/html/js/disable-buttons.js": "/dev/html/js/disable-buttons.js",
    "/dev/html/js/has-button-false.js": "/dev/html/js/has-button-false.js",
    "/dev/html/js/hidden-preloaded.js": "/dev/html/js/hidden-preloaded.js",
    "/dev/html/js/ihc-results.js": "/dev/html/js/ihc-results.js",
    "/dev/html/js/labs-ihc-results.js": "/dev/html/js/labs-ihc-results.js",
    "/dev/html/js/labs-results.js": "/dev/html/js/labs-results.js",
    "/dev/html/js/loading.js": "/dev/html/js/loading.js",
    "/dev/html/js/manage.js": "/dev/html/js/manage.js",
    "/dev/html/js/no-description.js": "/dev/html/js/no-description.js",
    "/dev/html/js/no-results.js": "/dev/html/js/no-results.js",
    "/dev/html/js/only-states.js": "/dev/html/js/only-states.js",
    "/dev/html/js/populate-zip.js": "/dev/html/js/populate-zip.js",
    "/dev/html/js/recommended.js": "/dev/html/js/recommended.js",
    "/dev/html/js/sample.js": "/dev/html/js/sample.js",
    "/dev/html/js/saturday-only.js": "/dev/html/js/saturday-only.js",
    "/dev/html/js/user-location.js": "/dev/html/js/user-location.js",
    "/dev/html/js/view-details.js": "/dev/html/js/view-details.js",
    "/dev/html/js/view-details-new.js": "/dev/html/js/view-details-new.js",
    "/findalab.js": "/findalab.js",
    "/findalab.css": "/findalab.css"
}
